manim_cad_drawing_utils/__init__.py
manim_cad_drawing_utils/dimensions.py
manim_cad_drawing_utils/hatch.py
manim_cad_drawing_utils/path_mapper.py
manim_cad_drawing_utils/round_corners.py
manim_cad_drawing_utils/utils.py
manim_cad_drawing_utils-0.0.5.dist-info/entry_points.txt
manim_cad_drawing_utils-0.0.5.dist-info/LICENSE.txt
manim_cad_drawing_utils-0.0.5.dist-info/METADATA
manim_cad_drawing_utils-0.0.5.dist-info/WHEEL
manim_cad_drawing_utils-0.0.5.dist-info/RECORD
