Metadata-Version: 2.3
Name: manim-CAD_Drawing_Utils
Version: 0.0.5
Summary: A collection of utility functions to for creating CAD-like visuals in Manim.
License: MIT
Author: GarryBGoode
Requires-Python: >=3.9
Classifier: Development Status :: 4 - Beta
Classifier: License :: OSI Approved :: MIT License
Classifier: Natural Language :: English
Classifier: Programming Language :: Python
Classifier: Programming Language :: Python :: 3
Classifier: Programming Language :: Python :: 3.9
Classifier: Programming Language :: Python :: 3.10
Classifier: Programming Language :: Python :: 3.11
Classifier: Programming Language :: Python :: 3.12
Classifier: Programming Language :: Python :: 3.13
Classifier: Topic :: Multimedia :: Graphics
Classifier: Topic :: Multimedia :: Video
Classifier: Topic :: Scientific/Engineering
Requires-Dist: manim (>=0.19.0,<=1.0)
Requires-Dist: scipy
Project-URL: Documentation, https://github.com/GarryBGoode/Manim_CAD_Drawing_utils
Project-URL: Repository, https://github.com/GarryBGoode/Manim_CAD_Drawing_utils
